picpro
