Metadata-Version: 2.1
Name: picpro
Version: 0.2.4
Summary: picpro a kitsrus PIC CLI programmer
Home-page: https://github.com/Salamek/picpro
Author: Adam Schubert
Author-email: adam.schubert@sg1-game.net
License: LGPL-3.0 
Project-URL: Release notes, https://github.com/Salamek/picpro/releases
Classifier: Development Status :: 5 - Production/Stable
Classifier: Environment :: Console
Classifier: Intended Audience :: Developers
Classifier: License :: OSI Approved :: GNU General Public License v2 (GPLv2)
Classifier: Operating System :: OS Independent
Classifier: Programming Language :: Python
Classifier: Programming Language :: Python :: 3
Classifier: Programming Language :: Python :: 3.9
Classifier: Programming Language :: Python :: 3.10
Classifier: Programming Language :: Python :: 3.11
Classifier: Programming Language :: Python :: 3.12
Classifier: Topic :: Software Development
Requires-Python: >=3.6
License-File: LICENSE
